shadow_project/__init__.py
shadow_project/cli.py
shadow_project/shadow_project.py
shadow_project-0.1.1.dist-info/DESCRIPTION.rst
shadow_project-0.1.1.dist-info/METADATA
shadow_project-0.1.1.dist-info/RECORD
shadow_project-0.1.1.dist-info/WHEEL
shadow_project-0.1.1.dist-info/entry_points.txt
shadow_project-0.1.1.dist-info/metadata.json
shadow_project-0.1.1.dist-info/top_level.txt
