Metadata-Version: 2.0
Name: shadow-project
Version: 0.1.1
Summary: A dummy project to evaluate the Cookie Cutter workflow
Home-page: https://github.com/balouf/shadow_project
Author: Fabien Mathieu
Author-email: fabien.mathieu@nokia-bell-labs.com
License: GNU General Public License v3
Keywords: shadow_project
Platform: UNKNOWN
Classifier: Development Status :: 2 - Pre-Alpha
Classifier: Intended Audience :: Developers
Classifier: License :: OSI Approved :: GNU General Public License v3 (GPLv3)
Classifier: Natural Language :: English
Classifier: Programming Language :: Python :: 3
Classifier: Programming Language :: Python :: 3.4
Classifier: Programming Language :: Python :: 3.5
Classifier: Programming Language :: Python :: 3.6
Requires-Dist: Click (>=6.0)
